BaruwaAPI/__init__.py
BaruwaAPI/endpoints.py
BaruwaAPI/exceptions.py
BaruwaAPI/resource.py
BaruwaAPI-0.0.5.dist-info/DESCRIPTION.rst
BaruwaAPI-0.0.5.dist-info/METADATA
BaruwaAPI-0.0.5.dist-info/RECORD
BaruwaAPI-0.0.5.dist-info/WHEEL
BaruwaAPI-0.0.5.dist-info/metadata.json
BaruwaAPI-0.0.5.dist-info/top_level.txt
