Metadata-Version: 2.0
Name: BaruwaAPI
Version: 0.0.5
Summary: Python bindings for Baruwa REST API
Home-page: https://github.com/baruwa-enterprise/BaruwaAPI
Author: Andrew Colin Kissa
Author-email: andrew@topdog.za.net
License: MPL 2.0
Keywords: baruwa api rest
Platform: UNKNOWN
Classifier: Development Status :: 3 - Alpha
Classifier: Programming Language :: Python
Classifier: Programming Language :: Python :: 2.6
Classifier: Programming Language :: Python :: 2.7
Classifier: Topic :: Software Development :: Libraries :: Python Modules
Classifier: Intended Audience :: Developers
Classifier: License :: OSI Approved :: Mozilla Public License 2.0 (MPL 2.0)
Classifier: Natural Language :: English
Classifier: Operating System :: OS Independent
Requires-Dist: restkit
